clask/__init__.py
clask/clask.py
clask/logger.py
clask/utils.py
clask/version.py
test/__init__.py
test/clask_demo.py
test/clask_test.py
test/flask_api.py
clask-0.0.5.dist-info/METADATA
clask-0.0.5.dist-info/WHEEL
clask-0.0.5.dist-info/top_level.txt
clask-0.0.5.dist-info/zip-safe
clask-0.0.5.dist-info/RECORD
