Metadata-Version: 2.1
Name: clask
Version: 0.0.5
Summary: a http client based on requests just like Flask
Home-page: https://github.com/mouday/Clask
Author: Peng Shiyu
Author-email: pengshiyuyx@gmail.com
License: MIT
Keywords: clask flask requests
Platform: UNKNOWN
Classifier: Programming Language :: Python :: 3.7
Requires-Dist: requests
